LICENSE
MANIFEST.in
README.md
setup.py
FaabDEVBeta/Faab.py
FaabDEVBeta/FaabFunction.py
FaabDEVBeta/FaabJWT.py
FaabDEVBeta/__init__.py
FaabDEVBeta/__version__.py
FaabDEVBeta/extensions.py
FaabDEVBeta/factory.py
FaabDEVBeta/utils.py
FaabDEVBeta.egg-info/PKG-INFO
FaabDEVBeta.egg-info/SOURCES.txt
FaabDEVBeta.egg-info/dependency_links.txt
FaabDEVBeta.egg-info/requires.txt
FaabDEVBeta.egg-info/top_level.txt
FaabDEVBeta/swag_config/__init__.py