Metadata-Version: 2.1
Name: FaabDEVBeta
Version: 0.1.5
Summary: This tool has the capability to automatically generate API endpoints based on the provided data model or database schema, encompassing operations such as creation, retrieval, updating, and deletion (CRUD). By doing so, it alleviates the burden on developers to manually write and configure these API endpoints, thus enhancing development efficiency. Furthermore, it can generate Swagger documentation, facilitating API debugging.
Home-page: https://github.com/OliverMao/FlaskAutoApiBuilder
Author: Yoobit Mao
Author-email: deewpoter@163.com
License: GLP
Classifier: Programming Language :: Python
Classifier: Programming Language :: Python :: 3
Classifier: Programming Language :: Python :: 3.6
Classifier: Programming Language :: Python :: Implementation :: CPython
Classifier: Programming Language :: Python :: Implementation :: PyPy
Requires-Python: >=3.6.0
License-File: LICENSE
